{
    "config.common.deprecated": "This option is deprecated",
    "config.common.enum.default.description": "使用 `.emmyrc.json` 中的值，或回退到默认值",
    "config.common.enum.off.description": "覆盖 `.emmyrc.json` 并禁用此选项",
    "config.common.enum.on.description": "覆盖 `.emmyrc.json` 并启用此选项",
    "config.emmylua.codeAction.insertSpace.description": "在插入 `@diagnostic disable-next-line` 时，在 `---` 注释后添加空格。",
    "config.emmylua.codeLens.enable.description": "启用代码透镜。",
    "config.emmylua.colors.global.description": "如果不为空，用指定颜色高亮全局变量",
    "config.emmylua.colors.local.description": "如果不为空，用指定颜色高亮局部变量",
    "config.emmylua.colors.mutableUnderline.description": "如果变量在作用域内被重新赋值，则为其添加下划线",
    "config.emmylua.colors.parameter.description": "如果不为空，用指定颜色高亮函数参数",
    "config.emmylua.completion.autoRequire.description": "自动插入 `require` 调用，当自动补全插入来自其他模块的对象时。",
    "config.emmylua.completion.baseFunctionIncludesName.description": "是否在基础函数补全中包含名称。效果：`function () end` -> `function name() end`。",
    "config.emmylua.completion.enable.description": "启用自动补全。",
    "config.emmylua.completion.postfix.description": "用于触发后缀自动补全的符号。",
    "config.emmylua.diagnostics.diagnosticInterval.description": "打开/更改文件与扫描错误之间的延迟（毫秒）。",
    "config.emmylua.documentColor.enable.description": "启用解析字符串中的颜色标签，并在旁边显示颜色选择器。",
    "config.emmylua.hint.enable.description": "启用内联提示。",
    "config.emmylua.hint.enumParamHint.description": "当向期望枚举的函数传递字面值时，显示枚举成员名称。\n\n示例：\n\n```lua\n--- @enum Level\nlocal Foo = {\n   Info = 1,\n   Error = 2,\n}\n\n--- @param l Level\nfunction print_level(l) end\n\nprint_level(1 --[[ 提示: Level.Info ]])\n```",
    "config.emmylua.hint.indexHint.description": "显示数组索引名称。\n\n示例：\n\n```lua\nlocal array = {\n   [1] = 1, -- [name]\n}\n\nprint(array[1] --[[ 提示: name ]])\n```",
    "config.emmylua.hint.localHint.description": "显示局部变量类型。",
    "config.emmylua.hint.metaCallHint.description": "当调用对象会触发其元表的 `__call` 函数时显示提示。",
    "config.emmylua.hint.overrideHint.description": "显示重写基类函数的方法。",
    "config.emmylua.hint.paramHint.description": "在函数调用中显示参数名，在函数定义中显示参数类型。",
    "config.emmylua.hover.enable.description": "启用悬停显示文档。",
    "config.emmylua.inlineValues.enable.description": "调试时显示内联值。",
    "config.emmylua.language.completeAnnotation.description": "在注解后换行时自动插入 `\"---\"`",
    "config.emmylua.ls.executablePath.description": "VSCode中指定可执行文件路径",
    "config.emmylua.ls.globalConfigPath.description": "指定全局配置文件的路径",
    "config.emmylua.ls.startParameters.description": "传递给EmmyLua语言服务器的附加参数",
    "config.emmylua.references.enable.description": "启用符号用法搜索。",
    "config.emmylua.references.fuzzySearch.description": "当普通搜索未找到任何内容时，使用模糊搜索查找符号用法。",
    "config.emmylua.references.shortStringSearch.description": "也在字符串中搜索用法。",
    "config.emmylua.semanticTokens.enable.description": "启用语义标记。",
    "config.emmylua.semanticTokens.renderDocumentationMarkup.description": "Render Markdown/RST in documentation. Set `doc.syntax` for this option to have effect.",
    "config.emmylua.workspace.enableReindex.description": "更改文件后启用整个项目的重新索引。",
    "config.emmylua.workspace.reindexDuration.description": "更改文件与整个项目重新索引之间的延迟（毫秒）。",
    "config.lua.trace.server.description": "在输出视图中跟踪 VSCode 与 EmmyLua 语言服务器之间的通信。默认值为 `off`",
    "debug.attach.captureLog": "捕获进程输出，显示在windows terminal上,该特性可能引发进程崩溃",
    "debug.attach.desc": "附加进程调试",
    "debug.attach.label": "EmmyLua: 通过进程ID附加",
    "debug.attach.name": "通过进程ID附加",
    "debug.attach.target_pid": "目标进程ID",
    "debug.attach.target_process": "通过名称过滤进程，如果目标唯一则直接附加",
    "debug.launch.arguments": "传递给可执行文件的参数",
    "debug.launch.blockOnExit": "进程结束时是否阻塞进程保持窗口开启",
    "debug.launch.desc": "启动程序，并使用附加调试器附加到进程调试",
    "debug.launch.label": "EmmyLua: 启动并附加程序",
    "debug.launch.name": "启动并附加程序",
    "debug.launch.newWindow": "emmylua会创建一个新窗口展示这个进程",
    "debug.launch.program": "启动并附加的可执行文件",
    "debug.launch.workingDir": "设置工作区"
}
